liblzcore.dylib
lzcomplexity.cpython-314-darwin.so
liblzcore.0.9.dylib
liblzcore.0.dylib
inc/PyLempelZiv.hpp
inc/PySequence.hpp
inc/utils.hpp
lzcomplexity.dylibs/liblzcore.0.9.dylib
lzcomplexity.dylibs/libtbb.12.10.dylib
lzcomplexity-0.9.6.dist-info/RECORD
lzcomplexity-0.9.6.dist-info/WHEEL
lzcomplexity-0.9.6.dist-info/top_level.txt
lzcomplexity-0.9.6.dist-info/METADATA
lzcomplexity-0.9.6.dist-info/licenses/LICENSE
