Metadata-Version: 2.4
Name: lzcomplexity
Version: 0.9.6
Summary: LempelZiv-76 complexity engine. Suited for complexity analysis of time series.
Author: Efren Aragon
Author-email: Efren Aragon <efrenaragon96@gmail.com>
License: MIT License
Classifier: Development Status :: 4 - Beta
Classifier: Environment :: Console
Classifier: Programming Language :: Python :: 3
Classifier: Programming Language :: C++
Classifier: Topic :: Software Development :: Libraries
Classifier: Topic :: Scientific/Engineering
Classifier: Topic :: Scientific/Engineering :: Information Analysis
Requires-Python: >=3.9
License-File: LICENSE
Dynamic: author
Dynamic: license-file
Dynamic: requires-python
